TaskMorph/__init__.py
TaskMorph/morph.py
taskmorph-0.2.dist-info/METADATA
taskmorph-0.2.dist-info/WHEEL
taskmorph-0.2.dist-info/RECORD
